Metadata-Version: 1.0
Name: Bayesian1990-Firstpackage
Version: 1.8
Summary: Probability distributions
Home-page: UNKNOWN
Author: Alessio Polymeropoulos
Author-email: polymeropoulos@hotmail.com
License: UNKNOWN
Platform: UNKNOWN
